{"content":[{"id":"702d1a15","settings":{"flex_direction":"row","flex_gap":{"unit":"px","size":0,"column":"0","row":"0"},"background_background":"classic","background_color":"#13182A","margin":{"unit":"px","top":"0","right":"0","bottom":"-110","left":"0","isLinked":false},"z_index":1000,"background_motion_fx_motion_fx_scrolling":"yes","background_motion_fx_opacity_range":{"unit":"%","size":"","sizes":{"start":100,"end":100}},"background_motion_fx_range":"page","motion_fx_motion_fx_scrolling":"yes","motion_fx_opacity_effect":"yes","motion_fx_opacity_level":{"unit":"px","size":1,"sizes":[]},"motion_fx_opacity_range":{"unit":"%","size":"","sizes":{"start":100,"end":100}},"motion_fx_range":"page","motion_fx_mouseTrack_effect":"yes","sticky":"top","sticky_effects_offset":20},"elements":[{"id":"2e46af3e","settings":{"flex_direction":"column","content_width":"full","width":{"unit":"%","size":36.613},"_flex_size":"none","_element_width":"initial"},"elements":[{"id":"1739e0c2","settings":{"content_width":"full","title":"SPHERE","link":{"url":"https:\/\/client.technologycraft.store\/sphere\/","is_external":"","nofollow":"","custom_attributes":""},"title_color":"#FFFFFF","typography_typography":"custom","typography_font_family":"Lexend","typography_font_size":{"unit":"px","size":30,"sizes":[]},"typography_font_weight":"600","_margin":{"unit":"px","top":"0","right":"0","bottom":"0","left":"60","isLinked":false}},"elements":[],"isInner":false,"widgetType":"heading","elType":"widget"}],"isInner":true,"elType":"container"},{"id":"30500c6","settings":{"flex_direction":"column","content_width":"full","width":{"unit":"%","size":56.374},"_flex_size":"none","_element_width":"initial"},"elements":[{"id":"7cb513ab","settings":{"content_width":"full","menu":"main-menu","_element_custom_width":{"unit":"%","size":100},"_flex_align_self":"flex-start","_transform_scale_effect_hover":{"unit":"px","size":1.05,"sizes":[]},"_transform_transition_hover":{"unit":"px","size":300,"sizes":[]},"menu_last_item":"cta","navmenu_align":"right","padding_horizontal_menu_item":{"unit":"px","size":20,"sizes":[]},"menu_space_between":{"unit":"px","size":10,"sizes":[]},"pointer":"text","menu_typography_typography":"custom","menu_typography_font_family":"Work Sans","menu_typography_font_size":{"unit":"px","size":16,"sizes":[]},"menu_typography_font_weight":"400","color_menu_item":"#FFFFFF","color_menu_item_hover":"#FFFFFF","padding":{"unit":"px","top":"10","right":"40","bottom":"10","left":"40","isLinked":false},"all_background_color_background":"classic","all_background_color_color":"#61CE7000","all_border_border":"solid","all_border_width":{"unit":"px","top":"1","right":"1","bottom":"1","left":"1","isLinked":true},"all_border_color":"#FFFFFF","_element_width":"initial","_flex_size":"none","all_border_radius":{"unit":"px","top":"6","right":"6","bottom":"6","left":"6","isLinked":true},"dropdown_close_icon":{"value":"fas fa-angle-up","library":"fa-solid"},"color_dropdown_item":"#FFFFFF","background_color_dropdown_item":"#838383","width_dropdown_item_tablet":{"unit":"px","size":100,"sizes":[]},"padding_horizontal_dropdown_item_tablet":{"unit":"px","size":30,"sizes":[]},"padding_vertical_dropdown_item_tablet":{"unit":"px","size":15,"sizes":[]},"toggle_color":"#FFFFFF","_element_custom_width_tablet":{"unit":"%","size":21,"sizes":[]},"_element_custom_width_mobile":{"unit":"%","size":"","sizes":[]},"_flex_align_self_tablet":"flex-end"},"elements":[],"isInner":false,"widgetType":"navigation-menu","elType":"widget"}],"isInner":true,"elType":"container"}],"isInner":false,"elType":"container"},{"id":"12af062b","settings":{"flex_direction":"column","boxed_width":{"unit":"px","size":1583,"sizes":[]},"min_height":{"unit":"px","size":890.438,"sizes":[]},"background_background":"video","background_video_link":"https:\/\/desaleemi.com\/deMastery\/wp-content\/uploads\/2022\/05\/phare-vid.m4v","background_video_fallback":{"url":"https:\/\/client.technologycraft.store\/sphere\/wp-content\/uploads\/2024\/08\/backdrop.jpg","id":28,"size":"","alt":"","source":"library"},"margin":{"unit":"px","top":"0","right":"0","bottom":"0","left":"0","isLinked":false},"_element_id":"lan-page"},"elements":[{"id":"7577f966","settings":{"flex_direction":"column","content_width":"full","width":{"unit":"%","size":65},"flex_justify_content":"center","flex_align_items":"center","margin":{"unit":"px","top":"280","right":"0","bottom":"0","left":"0","isLinked":false},"_flex_align_self":"center","_flex_size":"none","_element_width":"initial","width_tablet":{"unit":"%","size":86.455},"width_mobile":{"unit":"%","size":"","sizes":[]},"_element_width_tablet":"initial"},"elements":[{"id":"3a8fee5c","settings":{"content_width":"full","eael_fancy_text_prefix":"SPHERE IS A BEACON FOR","eael_fancy_text_strings":[{"eael_fancy_text_strings_text_field":"MANKIND","_id":"2333a7c"},{"eael_fancy_text_strings_text_field":"THE ENVIRONMENT","_id":"ea53c8d"},{"eael_fancy_text_strings_text_field":"CHANGE","_id":"b47482f"},{"_id":"fd65cb4","eael_fancy_text_strings_text_field":"OUR PLANET"},{"_id":"8f8bb18","eael_fancy_text_strings_text_field":"OUR OCEANS"},{"_id":"25d4a0a","eael_fancy_text_strings_text_field":"WILDLIFE"},{"_id":"cb212ec","eael_fancy_text_strings_text_field":"SUSTAINABILITY"},{"_id":"fc0b5c2","eael_fancy_text_strings_text_field":"CREATORS"}],"eael_fancy_text_suffix":"","eael_fancy_text_speed":80,"eael_fancy_text_delay":3000,"eael_fancy_text_prefix_color":"#FFFFFF","typography_typography":"custom","typography_font_family":"Lexend","typography_font_size":{"unit":"px","size":72,"sizes":[]},"eael_fancy_text_strings_typography_typography":"custom","eael_fancy_text_strings_typography_font_family":"Lexend","eael_fancy_text_strings_typography_font_size":{"unit":"px","size":72,"sizes":[]},"eael_fancy_text_strings_color":"#5DBDBB","eael_fancy_text_cursor_color":"#FFFFFF","eael_fancy_text_strings_margin":{"unit":"px","top":"14","right":"0","bottom":"0","left":"0","isLinked":false},"typography_font_size_tablet":{"unit":"px","size":45,"sizes":[]},"eael_fancy_text_strings_typography_font_size_tablet":{"unit":"px","size":45,"sizes":[]}},"elements":[],"isInner":false,"widgetType":"eael-fancy-text","elType":"widget"}],"isInner":true,"elType":"container"}],"isInner":false,"elType":"container"},{"id":"50a25454","settings":{"flex_direction":"column","background_background":"classic","background_color":"#13182A","box_shadow_box_shadow_type":"yes","box_shadow_box_shadow":{"horizontal":0,"vertical":1,"blur":16,"spread":9,"color":"rgba(0, 0, 0, 0.08)"},"padding":{"unit":"px","top":"130","right":"0","bottom":"130","left":"0","isLinked":false},"animation":"pulse","animation_duration":"slow","_element_id":"about"},"elements":[{"id":"3954202","settings":{"content_width":"full","title":"SPHERE is a social enterprise working to improve the future by connecting science and leading voices.","align":"center","title_color":"#FFFFFF","typography_typography":"custom","typography_font_family":"Lexend","typography_font_size":{"unit":"px","size":40,"sizes":[]},"typography_font_weight":"600","typography_line_height":{"unit":"px","size":56,"sizes":[]},"_element_width":"initial","_element_custom_width":{"unit":"%","size":81,"sizes":[]},"_flex_align_self":"center","_animation":"none","animation_duration":"slow","_transform_scale_effect":{"unit":"px","size":1.1,"sizes":[]}},"elements":[],"isInner":false,"widgetType":"heading","elType":"widget"},{"id":"47b3942f","settings":{"flex_direction":"row","flex_gap":{"unit":"px","size":0,"column":"0","row":"0"},"content_width":"full","width":{"unit":"%","size":82},"_flex_align_self":"center","_flex_size":"none","_element_width":"initial"},"elements":[{"id":"3f14a642","settings":{"flex_direction":"column","content_width":"full","width":{"unit":"%","size":50},"_flex_size":"none","_element_width":"initial"},"elements":[{"id":"2cdd90be","settings":{"content_width":"full","title":"At SPHERE, we are passionate about the world and believe we can engage the public by delivering compelling, productive content and utilising the power of social media.","title_color":"#FFFFFF","typography_typography":"custom","typography_font_family":"Work Sans","typography_font_size":{"unit":"px","size":20,"sizes":[]},"typography_font_weight":"400","typography_line_height":{"unit":"px","size":32,"sizes":[]},"_element_width":"initial","_element_custom_width":{"unit":"%","size":95.662},"_flex_size":"none"},"elements":[],"isInner":false,"widgetType":"heading","elType":"widget"}],"isInner":true,"elType":"container"},{"id":"245f95b4","settings":{"flex_direction":"column","content_width":"full","width":{"unit":"%","size":"50"}},"elements":[{"id":"73683b48","settings":{"content_width":"full","title":"To do so, we collaborate and work with pioneers, leaders and shapers, providing them tools to champion socially and environmentally crucial causes that connect with their audiences.","title_color":"#FFFFFF","typography_typography":"custom","typography_font_family":"Work Sans","typography_font_size":{"unit":"px","size":20,"sizes":[]},"typography_font_weight":"400","typography_line_height":{"unit":"px","size":32,"sizes":[]},"_element_width":"initial","_element_custom_width":{"unit":"%","size":91.533},"_flex_size":"none"},"elements":[],"isInner":false,"widgetType":"heading","elType":"widget"}],"isInner":true,"elType":"container"}],"isInner":true,"elType":"container"}],"isInner":false,"elType":"container"},{"id":"59f47e42","settings":{"flex_direction":"row","flex_gap":{"unit":"px","size":0,"column":"0","row":"0"},"background_background":"gradient","background_color":"#FFFFFF","background_color_stop":{"unit":"%","size":67,"sizes":[]},"background_color_b":"#5DBDBB","background_color_b_stop":{"unit":"%","size":0,"sizes":[]},"background_gradient_angle":{"unit":"deg","size":120,"sizes":[]},"padding":{"unit":"px","top":"80","right":"0","bottom":"80","left":"0","isLinked":false},"_element_id":"belikeus"},"elements":[{"id":"1bdf5617","settings":{"flex_direction":"column","content_width":"full","width":{"unit":"%","size":50},"_flex_size":"none","_element_width":"initial","padding_tablet":{"unit":"px","top":"10","right":"10","bottom":"10","left":"26","isLinked":false}},"elements":[{"id":"6bf99a42","settings":{"content_width":"full","title":"Be Like US","title_color":"#13182A","typography_typography":"custom","typography_font_family":"Lexend","typography_font_size":{"unit":"px","size":40,"sizes":[]},"typography_font_weight":"600","typography_text_transform":"uppercase"},"elements":[],"isInner":false,"widgetType":"heading","elType":"widget"},{"id":"186e9b87","settings":{"content_width":"full","title":"We are passionate about the world and believe we can engage the public by delivering compelling, productive content and utilizing the power of social media.","title_color":"#13182A","typography_typography":"custom","typography_font_family":"Work Sans","typography_font_size":{"unit":"px","size":16,"sizes":[]},"typography_font_weight":"400","typography_line_height":{"unit":"px","size":32,"sizes":[]},"_element_width":"initial","_element_custom_width":{"unit":"%","size":96,"sizes":[]}},"elements":[],"isInner":false,"widgetType":"heading","elType":"widget"},{"id":"44191579","settings":{"content_width":"full","title":"To do so, we collaborate and work with pioneers, leaders and shapers, providing them tools to champion socially and environmentally crucial causes that connect with their audiences. ","title_color":"#13182A","typography_typography":"custom","typography_font_family":"Work Sans","typography_font_size":{"unit":"px","size":16,"sizes":[]},"typography_font_weight":"400","typography_line_height":{"unit":"px","size":32,"sizes":[]},"_element_width":"initial","_element_custom_width":{"unit":"%","size":93,"sizes":[]}},"elements":[],"isInner":false,"widgetType":"heading","elType":"widget"}],"isInner":true,"elType":"container"},{"id":"5747ebb1","settings":{"flex_direction":"column","content_width":"full","width":{"unit":"%","size":50},"flex_align_items":"center","padding":{"unit":"px","top":"0","right":"0","bottom":"0","left":"0","isLinked":false},"_flex_size":"none","_element_width":"initial","flex_justify_content_tablet":"center"},"elements":[{"id":"318b4a9b","settings":{"content_width":"full","image":{"url":"https:\/\/client.technologycraft.store\/sphere\/wp-content\/uploads\/2024\/08\/pexels-mikhail-nilov-7474425-pnm2s0k9xj8e6b302n7si7vj7f93ar353oqqv0x92o.jpg","id":62,"size":"","alt":"","source":"library"},"_margin":{"unit":"px","top":"0","right":"0","bottom":"0","left":"0","isLinked":true},"_element_width":"initial","_element_custom_width":{"unit":"%","size":63,"sizes":[]},"_flex_align_self":"center","_mask_switch":"yes","_mask_size":"custom"},"elements":[],"isInner":false,"widgetType":"image","elType":"widget"}],"isInner":true,"elType":"container"}],"isInner":false,"elType":"container"},{"id":"4054fea7","settings":{"flex_direction":"column","background_background":"classic","background_image":{"url":"https:\/\/client.technologycraft.store\/sphere\/wp-content\/uploads\/2024\/08\/Phare_illustration_background.png","id":45,"size":"","alt":"","source":"library"},"background_attachment":"fixed","_element_id":"mission"},"elements":[{"id":"3fe409d4","settings":{"content_width":"full","title":"Our mission","align":"center","title_color":"#FFFFFF","typography_typography":"custom","typography_font_family":"Lexend","typography_font_size":{"unit":"px","size":40,"sizes":[]},"typography_font_weight":"600","typography_text_transform":"uppercase","typography_line_height":{"unit":"px","size":56,"sizes":[]},"_margin":{"unit":"px","top":"50","right":"0","bottom":"0","left":"0","isLinked":false},"_padding":{"unit":"px","top":"0","right":"0","bottom":"0","left":"0","isLinked":false},"_element_width":"initial","_element_custom_width":{"unit":"%","size":80,"sizes":[]},"_flex_align_self":"center","_animation":"none","animation_duration":"slow","_transform_scale_effect":{"unit":"px","size":1.1,"sizes":[]}},"elements":[],"isInner":false,"widgetType":"heading","elType":"widget"},{"id":"917017a","settings":{"flex_direction":"row","flex_gap":{"unit":"px","size":0,"column":"0","row":"0"},"background_background":"classic","background_image":{"url":"","id":"","size":"","alt":"","source":"library"},"background_attachment":"fixed","padding":{"unit":"px","top":"30","right":"10","bottom":"70","left":"10","isLinked":false},"content_width":"full"},"elements":[{"id":"3db3ee3f","settings":{"flex_direction":"column","content_width":"full","width":{"unit":"%","size":"50"},"background_background":"classic","background_color":"#13182A","border_radius":{"unit":"px","top":"9","right":"9","bottom":"9","left":"9","isLinked":true},"margin":{"unit":"px","top":"0","right":"30","bottom":"0","left":"0","isLinked":false},"padding":{"unit":"px","top":"40","right":"10","bottom":"40","left":"10","isLinked":false}},"elements":[{"id":"55b1b06d","settings":{"content_width":"full","text":"We Collect","align":"center","typography_typography":"custom","typography_font_family":"Lexend","typography_font_size":{"unit":"px","size":25,"sizes":[]},"typography_font_weight":"600","button_text_color":"#FFFFFF","background_color":"#61CE7000","border_border":"solid","text_padding":{"unit":"px","top":"20","right":"60","bottom":"20","left":"60","isLinked":false},"text_padding_tablet":{"unit":"px","top":"20","right":"20","bottom":"20","left":"20","isLinked":true}},"elements":[],"isInner":false,"widgetType":"button","elType":"widget"},{"id":"57d80561","settings":{"content_width":"full","margin":{"unit":"px","top":"-30","right":"0","bottom":"0","left":"0","isLinked":false}},"elements":[{"id":"6901f93e","settings":{"content_width":"full","image":{"url":"https:\/\/desaleemi.com\/deMastery\/wp-content\/uploads\/2022\/04\/Line-12x1024.jpg","id":"","size":"","source":"url"},"image_size":"custom","image_custom_dimension":{"width":"12","height":"80"},"align":"center","width":{"unit":"px","size":2,"sizes":[]},"width_tablet":{"unit":"px","size":"","sizes":[]},"width_mobile":{"unit":"px","size":"","sizes":[]},"height":{"unit":"px","size":60,"sizes":[]}},"elements":[],"isInner":false,"widgetType":"image","elType":"widget"}],"isInner":true,"elType":"container"},{"id":"3cb9ea9f","settings":{"content_width":"full","title":"Data, research and  information across key social and environmental topics","align":"center","title_color":"#FFFFFF","typography_typography":"custom","typography_font_family":"Work Sans","typography_font_size":{"unit":"px","size":18,"sizes":[]},"typography_font_weight":"400","typography_line_height":{"unit":"px","size":32,"sizes":[]},"_element_width":"initial","_element_custom_width":{"unit":"%","size":77,"sizes":[]},"_flex_align_self":"center"},"elements":[],"isInner":false,"widgetType":"heading","elType":"widget"},{"id":"65c8ff0a","settings":{"content_width":"full","image":{"url":"https:\/\/client.technologycraft.store\/sphere\/wp-content\/uploads\/2024\/08\/Phare_icon_1.png","id":42,"size":"","alt":"","source":"library"},"image_size":"thumbnail","_margin":{"unit":"px","top":"10","right":"0","bottom":"5","left":"0","isLinked":false}},"elements":[],"isInner":false,"widgetType":"image","elType":"widget"}],"isInner":true,"elType":"container"},{"id":"a60624d","settings":{"flex_direction":"column","content_width":"full","width":{"unit":"%","size":"50"},"background_background":"classic","background_color":"#13182A","border_radius":{"unit":"px","top":"9","right":"9","bottom":"9","left":"9","isLinked":true},"margin":{"unit":"px","top":"0","right":"30","bottom":"0","left":"0","isLinked":false},"padding":{"unit":"px","top":"40","right":"10","bottom":"40","left":"10","isLinked":false}},"elements":[{"id":"49d8c064","settings":{"content_width":"full","text":"To Provide","align":"center","typography_typography":"custom","typography_font_family":"Lexend","typography_font_size":{"unit":"px","size":25,"sizes":[]},"typography_font_weight":"600","button_text_color":"#FFFFFF","background_color":"#61CE7000","border_border":"solid","text_padding":{"unit":"px","top":"20","right":"60","bottom":"20","left":"60","isLinked":false},"text_padding_tablet":{"unit":"px","top":"20","right":"20","bottom":"20","left":"20","isLinked":true}},"elements":[],"isInner":false,"widgetType":"button","elType":"widget"},{"id":"6fd9f15f","settings":{"content_width":"full","margin":{"unit":"px","top":"-30","right":"0","bottom":"0","left":"0","isLinked":false}},"elements":[{"id":"5d7ca390","settings":{"content_width":"full","image":{"url":"https:\/\/desaleemi.com\/deMastery\/wp-content\/uploads\/2022\/04\/Line-12x1024.jpg","id":"","size":"","source":"url"},"image_size":"custom","image_custom_dimension":{"width":"12","height":"80"},"align":"center","width":{"unit":"px","size":2,"sizes":[]},"width_tablet":{"unit":"px","size":"","sizes":[]},"width_mobile":{"unit":"px","size":"","sizes":[]},"height":{"unit":"px","size":60,"sizes":[]}},"elements":[],"isInner":false,"widgetType":"image","elType":"widget"}],"isInner":true,"elType":"container"},{"id":"491fb0a7","settings":{"content_width":"full","title":"Brands, organisations and engaged citizens with helpful resources","align":"center","title_color":"#FFFFFF","typography_typography":"custom","typography_font_family":"Work Sans","typography_font_size":{"unit":"px","size":18,"sizes":[]},"typography_font_weight":"400","typography_line_height":{"unit":"px","size":32,"sizes":[]},"_element_width":"initial","_element_custom_width":{"unit":"%","size":57.498},"_flex_align_self":"center","_flex_size":"none"},"elements":[],"isInner":false,"widgetType":"heading","elType":"widget"},{"id":"75c075f0","settings":{"content_width":"full","image":{"url":"https:\/\/client.technologycraft.store\/sphere\/wp-content\/uploads\/2024\/08\/Phare_icon_2.png","id":43,"size":"","alt":"","source":"library"},"image_size":"thumbnail","_margin":{"unit":"px","top":"10","right":"0","bottom":"5","left":"0","isLinked":false}},"elements":[],"isInner":false,"widgetType":"image","elType":"widget"}],"isInner":true,"elType":"container"},{"id":"2613e67d","settings":{"flex_direction":"column","content_width":"full","width":{"unit":"%","size":"50"},"background_background":"classic","background_color":"#13182A","border_radius":{"unit":"px","top":"9","right":"9","bottom":"9","left":"9","isLinked":true},"padding":{"unit":"px","top":"40","right":"10","bottom":"40","left":"10","isLinked":false}},"elements":[{"id":"609285ef","settings":{"content_width":"full","text":"And Help","align":"center","typography_typography":"custom","typography_font_family":"Lexend","typography_font_size":{"unit":"px","size":25,"sizes":[]},"typography_font_weight":"600","button_text_color":"#FFFFFF","background_color":"#61CE7000","border_border":"solid","text_padding":{"unit":"px","top":"20","right":"60","bottom":"20","left":"60","isLinked":false},"text_padding_tablet":{"unit":"px","top":"20","right":"20","bottom":"20","left":"20","isLinked":true}},"elements":[],"isInner":false,"widgetType":"button","elType":"widget"},{"id":"2df1ea2f","settings":{"content_width":"full","margin":{"unit":"px","top":"-30","right":"0","bottom":"0","left":"0","isLinked":false}},"elements":[{"id":"749baa2d","settings":{"content_width":"full","image":{"url":"https:\/\/desaleemi.com\/deMastery\/wp-content\/uploads\/2022\/04\/Line-12x1024.jpg","id":"","size":"","source":"url"},"image_size":"custom","image_custom_dimension":{"width":"12","height":"80"},"align":"center","width":{"unit":"px","size":2,"sizes":[]},"width_tablet":{"unit":"px","size":"","sizes":[]},"width_mobile":{"unit":"px","size":"","sizes":[]},"height":{"unit":"px","size":60,"sizes":[]}},"elements":[],"isInner":false,"widgetType":"image","elType":"widget"}],"isInner":true,"elType":"container"},{"id":"19a9c4b9","settings":{"content_width":"full","title":"Leading voices share information the public want and need for a better future","align":"center","title_color":"#FFFFFF","typography_typography":"custom","typography_font_family":"Work Sans","typography_font_size":{"unit":"px","size":18,"sizes":[]},"typography_font_weight":"400","typography_line_height":{"unit":"px","size":32,"sizes":[]},"_element_width":"initial","_element_custom_width":{"unit":"%","size":74.298},"_flex_align_self":"center","_flex_size":"none"},"elements":[],"isInner":false,"widgetType":"heading","elType":"widget"},{"id":"4f7577bf","settings":{"content_width":"full","image":{"url":"https:\/\/client.technologycraft.store\/sphere\/wp-content\/uploads\/2024\/08\/Phare_icon_3.png","id":44,"size":"","alt":"","source":"library"},"image_size":"thumbnail","_margin":{"unit":"px","top":"10","right":"0","bottom":"5","left":"0","isLinked":false}},"elements":[],"isInner":false,"widgetType":"image","elType":"widget"}],"isInner":true,"elType":"container"}],"isInner":true,"elType":"container"}],"isInner":false,"elType":"container"},{"id":"2d989251","settings":{"flex_direction":"column","padding":{"unit":"px","top":"60","right":"10","bottom":"60","left":"10","isLinked":false},"_element_id":"topics"},"elements":[{"id":"4cac5e42","settings":{"content_width":"full","title":"Topics","align":"center","title_color":"#13182A","typography_typography":"custom","typography_font_family":"Lexend","typography_font_size":{"unit":"px","size":36,"sizes":[]},"typography_font_weight":"500","typography_text_transform":"uppercase"},"elements":[],"isInner":false,"widgetType":"heading","elType":"widget"},{"id":"3e2fb263","settings":{"flex_direction":"row","flex_gap":{"unit":"px","size":0,"column":"0","row":"0"},"content_width":"full"},"elements":[{"id":"42a34b61","settings":{"flex_direction":"column","content_width":"full","width":{"unit":"%","size":"25"}},"elements":[{"id":"4e795c01","settings":{"content_width":"full","image":{"url":"https:\/\/client.technologycraft.store\/sphere\/wp-content\/uploads\/2024\/08\/iStock-506164764.jpg","id":73,"size":"","alt":"","source":"library"},"image_size":"custom","image_custom_dimension":{"width":"260","height":"185"}},"elements":[],"isInner":false,"widgetType":"image","elType":"widget"},{"id":"72f283cb","settings":{"content_width":"full","title":"Food, Land-Use and Agriculture","title_color":"#000000","typography_typography":"custom","typography_font_family":"Work Sans","typography_font_size":{"unit":"px","size":16,"sizes":[]},"typography_font_weight":"500"},"elements":[],"isInner":false,"widgetType":"heading","elType":"widget"}],"isInner":true,"elType":"container"},{"id":"3bda976f","settings":{"flex_direction":"column","content_width":"full","width":{"unit":"%","size":"25"}},"elements":[{"id":"19ea6323","settings":{"content_width":"full","image":{"url":"https:\/\/client.technologycraft.store\/sphere\/wp-content\/uploads\/2024\/08\/image7.jpeg","id":31,"size":"","alt":"","source":"library"},"image_size":"custom","image_custom_dimension":{"width":"260","height":"185"}},"elements":[],"isInner":false,"widgetType":"image","elType":"widget"},{"id":"342c351d","settings":{"content_width":"full","title":"Habitats & Biodiversity","title_color":"#000000","typography_typography":"custom","typography_font_family":"Work Sans","typography_font_size":{"unit":"px","size":16,"sizes":[]},"typography_font_weight":"500"},"elements":[],"isInner":false,"widgetType":"heading","elType":"widget"}],"isInner":true,"elType":"container"},{"id":"50aace1f","settings":{"flex_direction":"column","content_width":"full","width":{"unit":"%","size":"25"}},"elements":[{"id":"7c4393b9","settings":{"content_width":"full","image":{"url":"https:\/\/client.technologycraft.store\/sphere\/wp-content\/uploads\/2024\/08\/image5.jpeg","id":30,"size":"","alt":"","source":"library"},"image_size":"custom","image_custom_dimension":{"width":"260","height":"185"}},"elements":[],"isInner":false,"widgetType":"image","elType":"widget"},{"id":"4083d4f6","settings":{"content_width":"full","title":"Technology, Innovation & IoT","title_color":"#000000","typography_typography":"custom","typography_font_family":"Work Sans","typography_font_size":{"unit":"px","size":16,"sizes":[]},"typography_font_weight":"500"},"elements":[],"isInner":false,"widgetType":"heading","elType":"widget"}],"isInner":true,"elType":"container"},{"id":"6f022064","settings":{"flex_direction":"column","content_width":"full","width":{"unit":"%","size":"25"}},"elements":[{"id":"706a7081","settings":{"content_width":"full","image":{"url":"https:\/\/client.technologycraft.store\/sphere\/wp-content\/uploads\/2024\/08\/image3.jpeg","id":72,"size":"","alt":"","source":"library"},"image_size":"custom","image_custom_dimension":{"width":"260","height":"185"}},"elements":[],"isInner":false,"widgetType":"image","elType":"widget"},{"id":"48dfc0e2","settings":{"content_width":"full","title":"Energy","title_color":"#000000","typography_typography":"custom","typography_font_family":"Work Sans","typography_font_size":{"unit":"px","size":16,"sizes":[]},"typography_font_weight":"500"},"elements":[],"isInner":false,"widgetType":"heading","elType":"widget"}],"isInner":true,"elType":"container"}],"isInner":true,"elType":"container"},{"id":"3f1dc6aa","settings":{"flex_direction":"row","flex_gap":{"unit":"px","size":0,"column":"0","row":"0"},"content_width":"full"},"elements":[{"id":"71c0b3d6","settings":{"flex_direction":"column","content_width":"full","width":{"unit":"%","size":"25"}},"elements":[{"id":"1ec96a1","settings":{"content_width":"full","image":{"url":"https:\/\/client.technologycraft.store\/sphere\/wp-content\/uploads\/2024\/08\/image4.jpeg","id":29,"size":"","alt":"","source":"library"},"image_size":"custom","image_custom_dimension":{"width":"260","height":"185"}},"elements":[],"isInner":false,"widgetType":"image","elType":"widget"},{"id":"5022e92c","settings":{"content_width":"full","title":"Economy","title_color":"#000000","typography_typography":"custom","typography_font_family":"Work Sans","typography_font_size":{"unit":"px","size":16,"sizes":[]},"typography_font_weight":"500"},"elements":[],"isInner":false,"widgetType":"heading","elType":"widget"}],"isInner":true,"elType":"container"},{"id":"6da3b6bf","settings":{"flex_direction":"column","content_width":"full","width":{"unit":"%","size":"25"}},"elements":[{"id":"122ce42a","settings":{"content_width":"full","image":{"url":"https:\/\/client.technologycraft.store\/sphere\/wp-content\/uploads\/2024\/08\/iStock-481252920-2-scaled-1.jpg","id":71,"size":"","alt":"","source":"library"},"image_size":"custom","image_custom_dimension":{"width":"260","height":"185"}},"elements":[],"isInner":false,"widgetType":"image","elType":"widget"},{"id":"43c69eb1","settings":{"content_width":"full","title":"Transport","title_color":"#000000","typography_typography":"custom","typography_font_family":"Work Sans","typography_font_size":{"unit":"px","size":16,"sizes":[]},"typography_font_weight":"500"},"elements":[],"isInner":false,"widgetType":"heading","elType":"widget"}],"isInner":true,"elType":"container"},{"id":"58bfea8a","settings":{"flex_direction":"column","content_width":"full","width":{"unit":"%","size":"25"}},"elements":[{"id":"7048e478","settings":{"content_width":"full","image":{"url":"https:\/\/client.technologycraft.store\/sphere\/wp-content\/uploads\/2024\/08\/image11.jpeg","id":34,"size":"","alt":"","source":"library"},"image_size":"custom","image_custom_dimension":{"width":"260","height":"185"}},"elements":[],"isInner":false,"widgetType":"image","elType":"widget"},{"id":"490db7f9","settings":{"content_width":"full","title":"Oceans & Water","title_color":"#000000","typography_typography":"custom","typography_font_family":"Work Sans","typography_font_size":{"unit":"px","size":16,"sizes":[]},"typography_font_weight":"500"},"elements":[],"isInner":false,"widgetType":"heading","elType":"widget"}],"isInner":true,"elType":"container"},{"id":"5b95da","settings":{"flex_direction":"column","content_width":"full","width":{"unit":"%","size":"25"}},"elements":[{"id":"2507c61d","settings":{"content_width":"full","image":{"url":"https:\/\/client.technologycraft.store\/sphere\/wp-content\/uploads\/2024\/08\/image12.jpeg","id":35,"size":"","alt":"","source":"library"},"image_size":"custom","image_custom_dimension":{"width":"260","height":"185"}},"elements":[],"isInner":false,"widgetType":"image","elType":"widget"},{"id":"81f9a51","settings":{"content_width":"full","title":"Built Environment","title_color":"#000000","typography_typography":"custom","typography_font_family":"Work Sans","typography_font_size":{"unit":"px","size":16,"sizes":[]},"typography_font_weight":"500"},"elements":[],"isInner":false,"widgetType":"heading","elType":"widget"}],"isInner":true,"elType":"container"}],"isInner":true,"elType":"container"},{"id":"59301df3","settings":{"flex_direction":"row","flex_gap":{"unit":"px","size":0,"column":"0","row":"0"},"content_width":"full"},"elements":[{"id":"2a647aa4","settings":{"flex_direction":"column","content_width":"full","width":{"unit":"%","size":"25"}},"elements":[{"id":"4ad00e8d","settings":{"content_width":"full","image":{"url":"https:\/\/client.technologycraft.store\/sphere\/wp-content\/uploads\/2024\/08\/image8.jpeg","id":32,"size":"","alt":"","source":"library"},"image_size":"custom","image_custom_dimension":{"width":"260","height":"185"}},"elements":[],"isInner":false,"widgetType":"image","elType":"widget"},{"id":"25f25369","settings":{"content_width":"full","title":"Cities","title_color":"#000000","typography_typography":"custom","typography_font_family":"Work Sans","typography_font_size":{"unit":"px","size":16,"sizes":[]},"typography_font_weight":"500"},"elements":[],"isInner":false,"widgetType":"heading","elType":"widget"}],"isInner":true,"elType":"container"},{"id":"66ded530","settings":{"flex_direction":"column","content_width":"full","width":{"unit":"%","size":"25"}},"elements":[{"id":"2193cc79","settings":{"content_width":"full","image":{"url":"https:\/\/client.technologycraft.store\/sphere\/wp-content\/uploads\/2024\/08\/image10.jpeg","id":33,"size":"","alt":"","source":"library"},"image_size":"custom","image_custom_dimension":{"width":"260","height":"185"}},"elements":[],"isInner":false,"widgetType":"image","elType":"widget"},{"id":"4b4ca6f4","settings":{"content_width":"full","title":"Health Fitness & Well-being","title_color":"#000000","typography_typography":"custom","typography_font_family":"Work Sans","typography_font_size":{"unit":"px","size":16,"sizes":[]},"typography_font_weight":"500"},"elements":[],"isInner":false,"widgetType":"heading","elType":"widget"}],"isInner":true,"elType":"container"},{"id":"8f8fbe9","settings":{"flex_direction":"column","content_width":"full","width":{"unit":"%","size":"25"}},"elements":[{"id":"b7ad529","settings":{"content_width":"full","image":{"url":"https:\/\/client.technologycraft.store\/sphere\/wp-content\/uploads\/2024\/08\/image17.jpeg","id":40,"size":"","alt":"","source":"library"},"image_size":"custom","image_custom_dimension":{"width":"260","height":"185"}},"elements":[],"isInner":false,"widgetType":"image","elType":"widget"},{"id":"c023955","settings":{"content_width":"full","title":"Business & Finance","title_color":"#000000","typography_typography":"custom","typography_font_family":"Work Sans","typography_font_size":{"unit":"px","size":16,"sizes":[]},"typography_font_weight":"500"},"elements":[],"isInner":false,"widgetType":"heading","elType":"widget"}],"isInner":true,"elType":"container"},{"id":"71d2dc59","settings":{"flex_direction":"column","content_width":"full","width":{"unit":"%","size":"25"}},"elements":[{"id":"327d7cd7","settings":{"content_width":"full","image":{"url":"https:\/\/client.technologycraft.store\/sphere\/wp-content\/uploads\/2024\/08\/image13.jpeg","id":36,"size":"","alt":"","source":"library"},"image_size":"custom","image_custom_dimension":{"width":"260","height":"185"}},"elements":[],"isInner":false,"widgetType":"image","elType":"widget"},{"id":"1fd0bf1c","settings":{"content_width":"full","title":"Industry","title_color":"#000000","typography_typography":"custom","typography_font_family":"Work Sans","typography_font_size":{"unit":"px","size":16,"sizes":[]},"typography_font_weight":"500"},"elements":[],"isInner":false,"widgetType":"heading","elType":"widget"}],"isInner":true,"elType":"container"}],"isInner":true,"elType":"container"},{"id":"75c2bf6f","settings":{"flex_direction":"row","flex_gap":{"unit":"px","size":0,"column":"0","row":"0"},"content_width":"full"},"elements":[{"id":"3b798579","settings":{"flex_direction":"column","content_width":"full","width":{"unit":"%","size":"25"}},"elements":[{"id":"7cf0c49f","settings":{"content_width":"full","image":{"url":"https:\/\/client.technologycraft.store\/sphere\/wp-content\/uploads\/2024\/08\/iStock-1064580446.jpg","id":41,"size":"","alt":"","source":"library"},"image_size":"custom","image_custom_dimension":{"width":"260","height":"185"}},"elements":[],"isInner":false,"widgetType":"image","elType":"widget"},{"id":"33e7a2e5","settings":{"content_width":"full","title":"Consumer Goods & Retail","title_color":"#000000","typography_typography":"custom","typography_font_family":"Work Sans","typography_font_size":{"unit":"px","size":16,"sizes":[]},"typography_font_weight":"500"},"elements":[],"isInner":false,"widgetType":"heading","elType":"widget"}],"isInner":true,"elType":"container"},{"id":"300add91","settings":{"flex_direction":"column","content_width":"full","width":{"unit":"%","size":"25"}},"elements":[{"id":"54d23bec","settings":{"content_width":"full","image":{"url":"https:\/\/client.technologycraft.store\/sphere\/wp-content\/uploads\/2024\/08\/image14.jpeg","id":37,"size":"","alt":"","source":"library"},"image_size":"custom","image_custom_dimension":{"width":"260","height":"185"}},"elements":[],"isInner":false,"widgetType":"image","elType":"widget"},{"id":"2a65fdd","settings":{"content_width":"full","title":"Diversity & Inclusion","title_color":"#000000","typography_typography":"custom","typography_font_family":"Work Sans","typography_font_size":{"unit":"px","size":16,"sizes":[]},"typography_font_weight":"500"},"elements":[],"isInner":false,"widgetType":"heading","elType":"widget"}],"isInner":true,"elType":"container"},{"id":"1c123aa4","settings":{"flex_direction":"column","content_width":"full","width":{"unit":"%","size":"25"}},"elements":[{"id":"32a8510a","settings":{"content_width":"full","image":{"url":"https:\/\/client.technologycraft.store\/sphere\/wp-content\/uploads\/2024\/08\/image15.jpeg","id":38,"size":"","alt":"","source":"library"},"image_size":"custom","image_custom_dimension":{"width":"260","height":"185"}},"elements":[],"isInner":false,"widgetType":"image","elType":"widget"},{"id":"736b266f","settings":{"content_width":"full","title":"Social Equality & Justice","title_color":"#000000","typography_typography":"custom","typography_font_family":"Work Sans","typography_font_size":{"unit":"px","size":16,"sizes":[]},"typography_font_weight":"500"},"elements":[],"isInner":false,"widgetType":"heading","elType":"widget"}],"isInner":true,"elType":"container"},{"id":"48152ca7","settings":{"flex_direction":"column","content_width":"full","width":{"unit":"%","size":"25"}},"elements":[{"id":"1c419b64","settings":{"content_width":"full","image":{"url":"https:\/\/client.technologycraft.store\/sphere\/wp-content\/uploads\/2024\/08\/image16.jpeg","id":39,"size":"","alt":"","source":"library"},"image_size":"custom","image_custom_dimension":{"width":"260","height":"185"}},"elements":[],"isInner":false,"widgetType":"image","elType":"widget"},{"id":"32a09f66","settings":{"content_width":"full","title":"Clean Air","title_color":"#000000","typography_typography":"custom","typography_font_family":"Work Sans","typography_font_size":{"unit":"px","size":16,"sizes":[]},"typography_font_weight":"500"},"elements":[],"isInner":false,"widgetType":"heading","elType":"widget"}],"isInner":true,"elType":"container"}],"isInner":true,"elType":"container"}],"isInner":false,"elType":"container"},{"id":"3a8c9745","settings":{"flex_direction":"column","background_background":"classic","background_color":"#AFDCDC","padding":{"unit":"px","top":"90","right":"0","bottom":"90","left":"0","isLinked":false}},"elements":[{"id":"a4d1179","settings":{"content_width":"full","width":{"unit":"%","size":88,"sizes":[]},"background_background":"classic","background_color":"#13182A","border_radius":{"unit":"px","top":"10","right":"10","bottom":"10","left":"10","isLinked":true},"box_shadow_box_shadow_type":"yes","box_shadow_box_shadow":{"horizontal":0,"vertical":0,"blur":10,"spread":0,"color":"#2F95AE"},"padding":{"unit":"px","top":"80","right":"80","bottom":"80","left":"80","isLinked":false},"_flex_align_self":"center"},"elements":[{"id":"6c7504a8","settings":{"content_width":"full","title":"Sign up for briefings","align":"center","title_color":"#FFFFFF","typography_typography":"custom","typography_font_family":"Lexend","typography_font_size":{"unit":"px","size":40,"sizes":[]},"typography_font_weight":"500","typography_text_transform":"uppercase","typography_line_height":{"unit":"px","size":56,"sizes":[]},"_margin":{"unit":"px","top":"0","right":"0","bottom":"0","left":"0","isLinked":false},"_padding":{"unit":"px","top":"0","right":"0","bottom":"0","left":"0","isLinked":false},"_element_width":"initial","_element_custom_width":{"unit":"%","size":80,"sizes":[]},"_flex_align_self":"center","_animation":"none","animation_duration":"slow","_transform_scale_effect":{"unit":"px","size":1.1,"sizes":[]}},"elements":[],"isInner":false,"widgetType":"heading","elType":"widget"},{"id":"1abb8d16","settings":{"content_width":"full","title":"Subscribe to stay in the loop and receive briefings on key societal and environmental topics","align":"center","title_color":"#FFFFFF","typography_typography":"custom","typography_font_family":"Work Sans","typography_font_size":{"unit":"px","size":16,"sizes":[]},"typography_font_weight":"400","typography_line_height":{"unit":"px","size":32,"sizes":[]},"_element_width":"initial","_element_custom_width":{"unit":"%","size":90.689},"_flex_align_self":"center","_flex_size":"none"},"elements":[],"isInner":false,"widgetType":"heading","elType":"widget"},{"id":"e63a497","settings":{"content_width":"full","mf_form_id":"99***1723480299578"},"elements":[],"isInner":false,"widgetType":"metform","elType":"widget"}],"isInner":true,"elType":"container"}],"isInner":false,"elType":"container"},{"id":"127184ba","settings":{"flex_direction":"row","flex_gap":{"unit":"px","size":0,"column":"0","row":"0"},"background_background":"classic","background_color":"#13182A","padding":{"unit":"px","top":"60","right":"0","bottom":"60","left":"0","isLinked":false}},"elements":[{"id":"61cfb2f1","settings":{"flex_direction":"column","content_width":"full","width":{"unit":"%","size":41},"margin":{"unit":"px","top":"0","right":"15","bottom":"0","left":"0","isLinked":false},"_flex_size":"none","_element_width":"initial"},"elements":[{"id":"220b601e","settings":{"content_width":"full","selected_icon":{"value":"fab fa-affiliatetheme","library":"fa-brands"},"align":"left","primary_color":"#5DBDBB","size":{"unit":"px","size":50,"sizes":[]},"_element_width":"initial","_element_custom_width":{"unit":"%","size":35.273},"_flex_size":"none"},"elements":[],"isInner":false,"widgetType":"icon","elType":"widget"},{"id":"2c7fffb1","settings":{"content_width":"full","title":"Sphere works with pioneers, leaders, and shapers, providing tools to champion socially and environmentally crucial causes, collaborate and connect with their audiences.","title_color":"#FFFFFF","typography_typography":"custom","typography_font_family":"Work Sans","typography_font_size":{"unit":"px","size":15,"sizes":[]},"typography_font_weight":"400","typography_line_height":{"unit":"px","size":27,"sizes":[]},"_margin":{"unit":"px","top":"5","right":"0","bottom":"0","left":"0","isLinked":false},"_element_width":"initial","_element_custom_width":{"unit":"%","size":100.03},"_flex_size":"none"},"elements":[],"isInner":false,"widgetType":"heading","elType":"widget"}],"isInner":true,"elType":"container"},{"id":"22788e0e","settings":{"flex_direction":"column","content_width":"full","width":{"unit":"%","size":21.262},"_flex_size":"none","_element_width":"initial"},"elements":[{"id":"38fdc721","settings":{"content_width":"full","title":"QUICK LINKS","title_color":"#FFFFFF","typography_typography":"custom","typography_font_family":"Prompt","typography_font_size":{"unit":"px","size":15,"sizes":[]},"typography_font_weight":"600"},"elements":[],"isInner":false,"widgetType":"heading","elType":"widget"},{"id":"31de4529","settings":{"content_width":"full","icon_list":[{"text":"About","selected_icon":{"value":"fas fa-arrow-circle-right","library":"fa-solid"},"_id":"f58d8ba"},{"text":"Be Like Us","selected_icon":{"value":"fas fa-arrow-circle-right","library":"fa-solid"},"_id":"dcb9a49"},{"text":"Mission","selected_icon":{"value":"fas fa-arrow-circle-right","library":"fa-solid"},"_id":"43049c7"},{"text":"Topics","selected_icon":{"value":"fas fa-arrow-circle-right","library":"fa-solid"},"_id":"212f1d3"},{"text":"Contact","selected_icon":{"value":"fas fa-arrow-circle-right","library":"fa-solid"},"_id":"17ac4f6"}],"space_between":{"unit":"px","size":12,"sizes":[]},"text_indent":{"unit":"px","size":20,"sizes":[]},"icon_typography_typography":"custom","icon_typography_font_family":"Work Sans","icon_typography_font_size":{"unit":"px","size":14,"sizes":[]},"icon_typography_font_weight":"400","text_shadow_text_shadow_type":"yes","text_color":"#FFFFFF","_element_width":"initial","_element_custom_width":{"unit":"%","size":81.484},"_flex_size":"none"},"elements":[],"isInner":false,"widgetType":"icon-list","elType":"widget"}],"isInner":true,"elType":"container"},{"id":"76eb1aac","settings":{"flex_direction":"column","content_width":"full","width":{"unit":"%","size":"50"}},"elements":[{"id":"739b2702","settings":{"content_width":"full","title":"CONTACT INFO","title_color":"#FFFFFF","typography_typography":"custom","typography_font_family":"Prompt","typography_font_size":{"unit":"px","size":15,"sizes":[]},"typography_font_weight":"600"},"elements":[],"isInner":false,"widgetType":"heading","elType":"widget"},{"id":"13f5c56e","settings":{"content_width":"full","icon_list":[{"text":" 123 Francois, San Francisco, CA 1234","selected_icon":{"value":"fas fa-map-marker-alt","library":"fa-solid"},"_id":"f58d8ba"},{"text":" 123-456-7890","selected_icon":{"value":"fas fa-phone","library":"fa-solid"},"link":{"url":"tel:1234567890","is_external":"","nofollow":"","custom_attributes":""},"_id":"dcb9a49"},{"text":"info@desaleemi.com","selected_icon":{"value":"fas fa-envelope","library":"fa-solid"},"link":{"url":"info@desaleemi.com","is_external":"","nofollow":"","custom_attributes":""},"_id":"43049c7"}],"space_between":{"unit":"px","size":20,"sizes":[]},"text_indent":{"unit":"px","size":20,"sizes":[]},"icon_typography_typography":"custom","icon_typography_font_family":"Work Sans","icon_typography_font_size":{"unit":"px","size":14,"sizes":[]},"icon_typography_font_weight":"400","text_shadow_text_shadow_type":"yes","text_color":"#FFFFFF","_margin":{"unit":"px","top":"10","right":"0","bottom":"0","left":"0","isLinked":false},"_element_width":"initial","_element_custom_width":{"unit":"%","size":100},"_flex_size":"none"},"elements":[],"isInner":false,"widgetType":"icon-list","elType":"widget"}],"isInner":true,"elType":"container"}],"isInner":false,"elType":"container"},{"id":"201b33bc","settings":{"flex_direction":"row","flex_gap":{"unit":"px","size":0,"column":"0","row":"0"},"background_background":"classic","background_color":"#13182A","border_border":"solid","border_width":{"unit":"px","top":"1","right":"0","bottom":"0","left":"0","isLinked":false},"border_color":"#5DBDBB"},"elements":[{"id":"6b2bf1cc","settings":{"flex_direction":"column","content_width":"full","width":{"unit":"%","size":"50"}},"elements":[{"id":"359053fa","settings":{"content_width":"full","title":"Copyright \u00a9 2022 | Sphere | All Rights Reserved.","header_size":"p","title_color":"#FFFFFF","typography_typography":"custom","typography_font_family":"Work Sans","typography_font_size":{"unit":"px","size":14,"sizes":[]},"typography_font_weight":"400","_margin":{"unit":"px","top":"0","right":"0","bottom":"24.5","left":"0","isLinked":false}},"elements":[],"isInner":false,"widgetType":"heading","elType":"widget"}],"isInner":true,"elType":"container"},{"id":"286352dc","settings":{"flex_direction":"column","content_width":"full","width":{"unit":"%","size":"50"},"flex_justify_content":"center"},"elements":[{"id":"2d4a5661","settings":{"content_width":"full","title":"Terms & Conditions","link":{"url":"#lan-page","is_external":"","nofollow":"","custom_attributes":""},"header_size":"p","align":"right","title_color":"#FFFFFF","typography_typography":"custom","typography_font_family":"Work Sans","typography_font_size":{"unit":"px","size":14,"sizes":[]},"typography_font_weight":"400","_margin":{"unit":"px","top":"0","right":"0","bottom":"24.5","left":"0","isLinked":false},"_padding":{"unit":"px","top":"15","right":"0","bottom":"0","left":"0","isLinked":false}},"elements":[],"isInner":false,"widgetType":"heading","elType":"widget"}],"isInner":true,"elType":"container"}],"isInner":false,"elType":"container"}],"page_settings":{"eael_ext_toc_title":"Table of Contents"},"version":"0.4","title":"sphere","type":"page"}